evi/__init__.py
evi/evi.cpython-311-aarch64-linux-gnu.so
evi/cli/keygen.py
evi/include/alea/alea.h
evi/include/alea/algorithms.h
evi/include/deb/CKKSTypes.hpp
evi/include/deb/Constant.hpp
evi/include/deb/Context.hpp
evi/include/deb/Decryptor.hpp
evi/include/deb/Encryptor.hpp
evi/include/deb/KeyGenerator.hpp
evi/include/deb/Macro.hpp
evi/include/deb/SecretKeyGenerator.hpp
evi/include/deb/SeedGenerator.hpp
evi/include/deb/Serialize.hpp
evi/include/deb/Types.hpp
evi/include/deb/utils/Basic.hpp
evi/include/deb/utils/FFT.hpp
evi/include/deb/utils/ModArith.hpp
evi/include/deb/utils/NTT.hpp
evi/include/deb/utils/Span.hpp
evi/include/generated/DebFBType.h
evi/include/generated/DebParam.hpp
evi/lib/libalea.a
evi/lib/libevi_crypto.so
evi/lib/cmake/alea/aleaConfig.cmake
evi/lib/cmake/alea/aleaTargets-release.cmake
evi/lib/cmake/alea/aleaTargets.cmake
evi/lib64/libdeb.a
evi/lib64/libevi_crypto.so
evi/lib64/cmake/deb/debConfig.cmake
evi/lib64/cmake/deb/debConfigVersion.cmake
evi/lib64/cmake/deb/debTargets-release.cmake
evi/lib64/cmake/deb/debTargets.cmake
evi/share/deb/licenses/LICENSE
pyenvector/__init__.py
pyenvector/api/__init__.py
pyenvector/api/connection.py
pyenvector/api/grpc.py
pyenvector/cli/pyenvector_keygen.py
pyenvector/client/__init__.py
pyenvector/client/client.py
pyenvector/crypto/__init__.py
pyenvector/crypto/block.py
pyenvector/crypto/cipher.py
pyenvector/crypto/context.py
pyenvector/crypto/decryptor.py
pyenvector/crypto/encryptor.py
pyenvector/crypto/key_manager.py
pyenvector/crypto/parameter.py
pyenvector/index/__init__.py
pyenvector/index/index.py
pyenvector/proto_gen/__init__.py
pyenvector/proto_gen/common_message_pb2.py
pyenvector/proto_gen/common_message_pb2_grpc.py
pyenvector/proto_gen/type_pb2.py
pyenvector/proto_gen/type_pb2_grpc.py
pyenvector/proto_gen/es2e/es2e_api_pb2.py
pyenvector/proto_gen/es2e/es2e_api_pb2_grpc.py
pyenvector/proto_gen/es2e/es2e_message_pb2.py
pyenvector-1.2.2.dist-info/METADATA
pyenvector-1.2.2.dist-info/WHEEL
pyenvector-1.2.2.dist-info/entry_points.txt
pyenvector-1.2.2.dist-info/RECORD
pyenvector-1.2.2.dist-info/licenses/LICENSE
pyenvector-1.2.2.dist-info/sboms/auditwheel.cdx.json
